nexus_client/__init__.py
nexus_client/_compat.py
nexus_client/async_client.py
nexus_client/client.py
nexus_client/exceptions.py
nexus_client/protocol.py
nexus_client/langgraph/__init__.py
nexus_client/langgraph/client.py
nexus_client/langgraph/tools.py
nexus_fs_python-0.1.0.dist-info/licenses/LICENSE
nexus_fs_python-0.1.0.dist-info/METADATA
nexus_fs_python-0.1.0.dist-info/WHEEL
nexus_fs_python-0.1.0.dist-info/top_level.txt
nexus_fs_python-0.1.0.dist-info/RECORD
