Metadata-Version: 2.4
Name: nexus-fs-python
Version: 0.1.0
Summary: Lightweight Python 3.11+ client SDK for Nexus filesystem, designed for LangGraph deployments
Author: Nexus Team
License-Expression: Apache-2.0
Project-URL: Homepage, https://github.com/nexi-lab/nexus-python
Project-URL: Documentation, https://github.com/nexi-lab/nexus-python#readme
Project-URL: Repository, https://github.com/nexi-lab/nexus-python
Project-URL: Issues, https://github.com/nexi-lab/nexus-python/issues
Keywords: nexus,filesystem,client,sdk,langgraph,ai,agents
Classifier: Development Status :: 3 - Alpha
Classifier: Intended Audience :: Developers
Classifier: Programming Language :: Python :: 3
Classifier: Programming Language :: Python :: 3.11
Classifier: Programming Language :: Python :: 3.12
Classifier: Programming Language :: Python :: 3.13
Classifier: Topic :: Software Development :: Libraries :: Python Modules
Classifier: Topic :: System :: Filesystems
Requires-Python: >=3.11
License-File: LICENSE
Requires-Dist: httpx>=0.27.0
Requires-Dist: tenacity>=8.0.0
Requires-Dist: pydantic>=2.0.0
Provides-Extra: langgraph
Requires-Dist: langchain-core>=0.3.0; extra == "langgraph"
Requires-Dist: langgraph>=0.2.0; extra == "langgraph"
Provides-Extra: dev
Requires-Dist: pytest>=8.0.0; extra == "dev"
Requires-Dist: pytest-asyncio>=0.24.0; extra == "dev"
Requires-Dist: ruff>=0.1.0; extra == "dev"
Requires-Dist: mypy>=1.0.0; extra == "dev"
Dynamic: license-file
